jl95/pytools/ppjava.py
jl95terceira/pytools/ppjava.py
jl95terceira_pytools_pp_java-0.1.1.dist-info/METADATA
jl95terceira_pytools_pp_java-0.1.1.dist-info/WHEEL
jl95terceira_pytools_pp_java-0.1.1.dist-info/RECORD
