Metadata-Version: 2.4
Name: jl95terceira_pytools_pp_java
Version: 0.1.1
Summary: A processor / source generator for Java
Project-URL: Homepage, https://github.com/jl95terceira/project-pytools-pp-java
Project-URL: Issues, https://github.com/jl95terceira/project-pytools-pp-java/issues
Author-email: Joao Luis Ornelas da Silva <jl95terceira@gmail.com>
Classifier: License :: OSI Approved :: MIT License
Classifier: Operating System :: OS Independent
Classifier: Programming Language :: Python :: 3
Requires-Python: >=3.12
Requires-Dist: jl95terceira-pytools-pp>=0.3.1
